disnake_paginator/__init__.py
disnake_paginator/disnake_paginator.py
disnake_paginator/paginators.py
disnake_paginator/wrappers.py
disnake_paginator-1.0.8.dist-info/LICENSE
disnake_paginator-1.0.8.dist-info/METADATA
disnake_paginator-1.0.8.dist-info/WHEEL
disnake_paginator-1.0.8.dist-info/top_level.txt
disnake_paginator-1.0.8.dist-info/RECORD
