Metadata-Version: 2.1
Name: disnake-paginator
Version: 1.0.8
Summary: This is a module that contains paginators for disnake
Home-page: https://github.com/ErrorNoInternet/disnake-paginator
Author: ErrorNoInternet
License: MIT
Keywords: discord,disnake,paginator
Classifier: Development Status :: 5 - Production/Stable
Classifier: Intended Audience :: Developers
Classifier: License :: OSI Approved :: MIT License
Classifier: Programming Language :: Python :: 3
Classifier: Programming Language :: Python :: 3.8
Classifier: Programming Language :: Python :: 3.9
Classifier: Programming Language :: Python :: 3.10
Classifier: Programming Language :: Python :: 3.11
License-File: LICENSE
Requires-Dist: disnake
